MANIFEST.in
README.rst
setup.cfg
setup.py
BeakerHelpers.egg-info/PKG-INFO
BeakerHelpers.egg-info/SOURCES.txt
BeakerHelpers.egg-info/dependency_links.txt
BeakerHelpers.egg-info/entry_points.txt
BeakerHelpers.egg-info/namespace_packages.txt
BeakerHelpers.egg-info/not-zip-safe
BeakerHelpers.egg-info/requires.txt
BeakerHelpers.egg-info/top_level.txt
beakerhelpers/__init__.py
beakerhelpers/sessions.py