Metadata-Version: 1.0
Name: BeakerHelpers
Version: 0.1
Summary: An extendable Beaker helpers package to manage Beaker sessions
Home-page: UNKNOWN
Author: Linas Juškevičius
Author-email: linas.juskevicius@gmail.com
License: MIT
Keywords: paste beaker session database active
Platform: UNKNOWN
